schwifty/__init__.py
schwifty/bban.py
schwifty/bic.py
schwifty/common.py
schwifty/domain.py
schwifty/exceptions.py
schwifty/iban.py
schwifty/py.typed
schwifty/registry.py
schwifty/bank_registry/README.md
schwifty/bank_registry/generated_at.json
schwifty/bank_registry/generated_ba.json
schwifty/bank_registry/generated_be.json
schwifty/bank_registry/generated_ch.json
schwifty/bank_registry/generated_cz.json
schwifty/bank_registry/generated_de.json
schwifty/bank_registry/generated_ee.json
schwifty/bank_registry/generated_es.json
schwifty/bank_registry/generated_fi.json
schwifty/bank_registry/generated_ge.json
schwifty/bank_registry/generated_hr.json
schwifty/bank_registry/generated_hu.json
schwifty/bank_registry/generated_it.json
schwifty/bank_registry/generated_kz.json
schwifty/bank_registry/generated_li.json
schwifty/bank_registry/generated_lt.json
schwifty/bank_registry/generated_lv.json
schwifty/bank_registry/generated_md.json
schwifty/bank_registry/generated_nl.json
schwifty/bank_registry/generated_no.json
schwifty/bank_registry/generated_pl.json
schwifty/bank_registry/generated_ro.json
schwifty/bank_registry/generated_rs.json
schwifty/bank_registry/generated_se.json
schwifty/bank_registry/generated_si.json
schwifty/bank_registry/generated_sk.json
schwifty/bank_registry/generated_ua.json
schwifty/bank_registry/manual_ad.json
schwifty/bank_registry/manual_ae.json
schwifty/bank_registry/manual_bg.json
schwifty/bank_registry/manual_cr.json
schwifty/bank_registry/manual_cy.json
schwifty/bank_registry/manual_dk.v2.json
schwifty/bank_registry/manual_es.json
schwifty/bank_registry/manual_fr.json
schwifty/bank_registry/manual_gb.json
schwifty/bank_registry/manual_gr.json
schwifty/bank_registry/manual_ie.json
schwifty/bank_registry/manual_il.json
schwifty/bank_registry/manual_is.json
schwifty/bank_registry/manual_it.json
schwifty/bank_registry/manual_lu.json
schwifty/bank_registry/manual_mc.json
schwifty/bank_registry/manual_me.json
schwifty/bank_registry/manual_pt.json
schwifty-2025.9.0.dist-info/METADATA
schwifty-2025.9.0.dist-info/WHEEL
schwifty-2025.9.0.dist-info/licenses/LICENSE
schwifty-2025.9.0.dist-info/RECORD
