Metadata-Version: 2.4
Name: schwifty
Version: 2025.9.0
Summary: IBAN parsing and validation
Project-URL: Changelog, https://github.com/mdomke/schwifty/blob/main/CHANGELOG.rst
Project-URL: Documentation, https://schwifty.readthedocs.io/en/latest/
Project-URL: Homepage, http://github.com/mdomke/schwifty
Author-email: Martin Domke <mail@martindomke.net>
License-Expression: MIT
License-File: LICENSE
Classifier: Development Status :: 5 - Production/Stable
Classifier: Intended Audience :: Developers
Classifier: License :: OSI Approved :: MIT License
Classifier: Operating System :: OS Independent
Classifier: Programming Language :: Python
Classifier: Programming Language :: Python :: 3
Classifier: Programming Language :: Python :: 3.9
Classifier: Programming Language :: Python :: 3.10
Classifier: Programming Language :: Python :: 3.11
Classifier: Programming Language :: Python :: 3.12
Classifier: Programming Language :: Python :: 3.13
Classifier: Topic :: Office/Business :: Financial
Requires-Python: >=3.9
Requires-Dist: importlib-resources>=5.10; python_version <= '3.11'
Requires-Dist: pycountry
Requires-Dist: rstr
Requires-Dist: typing-extensions>=4.0.1; python_version <= '3.10'
Provides-Extra: pydantic
Requires-Dist: pydantic>=2.0; extra == 'pydantic'
